<ui:UiBinder xmlns:ui='urn:ui:com.google.gwt.uibinder'
    xmlns:g='urn:import:com.google.gwt.user.client.ui'>
     <ui:style>
     	.centered{
		margin: 0 auto;
	}
     </ui:style>
  	<g:VerticalPanel styleName='{style.centered}'>
  		<g:Label text="CPR:"/>
  		<g:TextBox ui:field="username"/>
  		<g:Label text="Password:"/>
  		<g:PasswordTextBox ui:field="password"/>
  		<g:Label text="" ui:field="feedback"/>
  		<g:Button ui:field="submit" text="submit"/>
  	</g:VerticalPanel>	
  </ui:UiBinder>